androguard/__init__.py
androguard/cli/__init__.py
androguard/cli/cli.py
androguard/cli/main.py
androguard/core/__init__.py
androguard/core/analysis/__init__.py
androguard/core/analysis/analysis.py
androguard/core/androconf.py
androguard/core/api_specific_resources/__init__.py
androguard/core/api_specific_resources/aosp_permissions/permissions_10.json
androguard/core/api_specific_resources/aosp_permissions/permissions_13.json
androguard/core/api_specific_resources/aosp_permissions/permissions_14.json
androguard/core/api_specific_resources/aosp_permissions/permissions_15.json
androguard/core/api_specific_resources/aosp_permissions/permissions_16.json
androguard/core/api_specific_resources/aosp_permissions/permissions_17.json
androguard/core/api_specific_resources/aosp_permissions/permissions_18.json
androguard/core/api_specific_resources/aosp_permissions/permissions_19.json
androguard/core/api_specific_resources/aosp_permissions/permissions_21.json
androguard/core/api_specific_resources/aosp_permissions/permissions_22.json
androguard/core/api_specific_resources/aosp_permissions/permissions_23.json
androguard/core/api_specific_resources/aosp_permissions/permissions_24.json
androguard/core/api_specific_resources/aosp_permissions/permissions_25.json
androguard/core/api_specific_resources/aosp_permissions/permissions_26.json
androguard/core/api_specific_resources/aosp_permissions/permissions_27.json
androguard/core/api_specific_resources/aosp_permissions/permissions_28.json
androguard/core/api_specific_resources/aosp_permissions/permissions_29.json
androguard/core/api_specific_resources/aosp_permissions/permissions_30.json
androguard/core/api_specific_resources/aosp_permissions/permissions_31.json
androguard/core/api_specific_resources/aosp_permissions/permissions_32.json
androguard/core/api_specific_resources/aosp_permissions/permissions_33.json
androguard/core/api_specific_resources/aosp_permissions/permissions_34.json
androguard-4.1.0.dist-info/LICENCE-2.0
androguard-4.1.0.dist-info/METADATA
androguard-4.1.0.dist-info/WHEEL
androguard-4.1.0.dist-info/entry_points.txt
androguard-4.1.0.dist-info/RECORD
